Metadata-Version: 2.1
Name: cryptoEx
Version: 0.0.3
Summary: A simple API for some cryptocurrency exchanges
Home-page: https://github.com/jtc1246/cryptoEx
Author: Tiancheng Jiao
Author-email: jtc1246@outlook.com
License: GPL-2.0 License
Platform: all
Requires-Python: >=3
License-File: LICENSE
